MANIFEST.in
README.md
setup.py
pyhttp/Exceptions.py
pyhttp/Request.py
pyhttp/Response.py
pyhttp/__init__.py
pyrequest.egg-info/PKG-INFO
pyrequest.egg-info/SOURCES.txt
pyrequest.egg-info/dependency_links.txt
pyrequest.egg-info/requires.txt
pyrequest.egg-info/top_level.txt