Metadata-Version: 1.0
Name: pyrequest
Version: 0.5
Summary: Pythonic way of HTTP request
Home-page: https://github.com/plasmashadow/pyhttp.git
Author: plasmashadow
Author-email: plasmashadowx@gmail.com
License: MIT License
Platform: UNKNOWN
Classifier: Programming Language :: Python
Classifier: Programming Language :: Python :: 2
Classifier: Intended Audience :: Developers
